note.py
note.py-0.1.1.dist-info/LICENSE
note.py-0.1.1.dist-info/METADATA
note.py-0.1.1.dist-info/WHEEL
note.py-0.1.1.dist-info/entry_points.txt
note.py-0.1.1.dist-info/top_level.txt
note.py-0.1.1.dist-info/RECORD
